README.md
pylint_codeclimate_reporter.py
setup.py
pylint_codeclimate_reporter.egg-info/PKG-INFO
pylint_codeclimate_reporter.egg-info/SOURCES.txt
pylint_codeclimate_reporter.egg-info/dependency_links.txt
pylint_codeclimate_reporter.egg-info/not-zip-safe
pylint_codeclimate_reporter.egg-info/requires.txt
pylint_codeclimate_reporter.egg-info/top_level.txt